<?xml version="1.0" encoding="UTF-8"?>
<odoo>

	<template id="s_one_page_para_with_four_imgs" name="Left features and right side images">
		<section
			class="s_one_page_para_with_four_imgs bg-light-1 spacer">
			<div class="feature12" id="service">
				<div class="container">
					<div class="row">
						<div class="col-lg-6">
							<h2 class="m-b-30 m-t-20 text-beta">Awesome with Extra Ordinary Flexibility &amp;
								Features
							</h2>
							<h4 class="text-muted font-light">You can relay on our amazing features list and
								also our customer services will be great experience for you
								without doubt and in no-time
							</h4>
							<div class="row">
								<div class="col-md-6 m-t-30">
									<h5 class="font-medium">Instant Solutions</h5>
									<p class="custom_p">You can relay on our amazing features list and
										also our
										customer services will.
									</p>
								</div>
								<div class="col-md-6 m-t-30">
									<h5 class="font-medium">Retargeting Market</h5>
									<p class="custom_p">You can relay on our amazing features list and
										also our
										customer services will.
									</p>
								</div>
								<div class="col-md-6 m-t-30">
									<h5 class="font-medium">Fruitful Results</h5>
									<p class="custom_p">You can relay on our amazing features list and
										also our
										customer services will.
									</p>
								</div>
								<div class="col-md-6 m-t-30">
									<h5 class="font-medium">100% Satisfection</h5>
									<p class="custom_p">You can relay on our amazing features list and
										also our
										customer services will.
									</p>
								</div>
								<div class="col-lg-12 m-t-30 m-b-30 s_btn" data-name="Button">
									<a class="btn btn-alpha rounded-circle btn-md arrow-btn bizople_button"
										 href="#">
											View Other Features
											<span class="fa fa-1x fa-fw fa-long-arrow-right ml-1"></span>
									</a>
								</div>
							</div>
						</div>
						<div class="col-lg-6">
							<div class="row wrap-feature-12">
								<div class="col-md-6 ">
									<div class="row">
										<div class="col-md-12">
											<img src="/theme_centric/static/src/img/img3_o.jpg"
												class="rounded img-shadow img-responsive img img-fluid" alt="" />
										</div>
										<div class="col-md-12 ">
											<img src="/theme_centric/static/src/img/img4_o.jpg"
												class="rounded img-shadow img-responsive img img-fluid" alt="" />
										</div>
									</div>
								</div>
								<div class="col-md-6 uneven-box ">
									<div class="row">
										<div class="col-md-12 ">
											<img src="/theme_centric/static/src/img/img5_o.jpg"
												class="rounded img-shadow img-responsive img img-fluid" alt="" />
										</div>
										<div class="col-md-12 ">
											<img src="/theme_centric/static/src/img/img6_o.jpg"
												class="rounded img-shadow img-responsive img img-fluid" alt="" />
										</div>
									</div>
								</div>
							</div>
						</div>
					</div>
				</div>
			</div>
		</section>

	</template>

</odoo>