<?xml version="1.0" encoding="utf-8"?>
<odoo>
    <data>

		<record id="view_sorna_eway" model="ir.ui.view">
            <field name="name">acs.eway.fields</field>
            <field name="model">account.move</field>
			<field name="inherit_id" ref="account.view_move_form"/>
            <!--field name="type">form</field-->
            <field name="arch" type="xml">
                <field name="ref" position="after">                                              
                    <field name="enable_eway"/>
                    <field name="bill_no"  attrs="{'invisible':[('enable_eway','!=',True)]}"/>
					<field name="tran_name"  attrs="{'invisible':[('enable_eway','!=',True)]}"/>
					<field name="del_thr"  attrs="{'invisible':[('enable_eway','!=',True)]}"/>
					<field name="veh_no"  attrs="{'invisible':[('enable_eway','!=',True)]}"/>
                </field>  
			</field>
		</record>
	</data>
</odoo>
			